README.rst
setup.py
features/steps/__init__.py
pythonrestclient/__init__.py
pythonrestclient/service_factory.py
pythonrestclient.egg-info/PKG-INFO
pythonrestclient.egg-info/SOURCES.txt
pythonrestclient.egg-info/dependency_links.txt
pythonrestclient.egg-info/requires.txt
pythonrestclient.egg-info/top_level.txt
pythonrestclient/api/__init__.py
pythonrestclient/api/client_class.py
pythonrestclient/api/errors.py
pythonrestclient/models/__init__.py
pythonrestclient/models/abstract_model.py
pythonrestclient/models/collection_class.py
pythonrestclient/models/post_model.py