Metadata-Version: 1.1
Name: pythonrestclient
Version: 1.2.0
Summary: Python rest client
Home-page: https://github.com/Hawk73/python-rest-client
Author: Hawk73
Author-email: hawk.bms@gmail.com
License: MIT
Keywords: rest api client
Platform: UNKNOWN
Classifier: Development Status :: 4 - Beta
Classifier: Intended Audience :: Developers
Classifier: Topic :: Software Development :: Build Tools
Classifier: License :: OSI Approved :: MIT License
Classifier: Programming Language :: Python :: 2.7
